[
	{
		"name": "cirrus_container-4",
		"cat": "job",
		"ph": "B",
		"ts": "0",
		"pid": "0",
		"tid": "4"
	},
	{
		"name": "cirrus_container-8",
		"cat": "job",
		"ph": "B",
		"ts": "1000000",
		"pid": "0",
		"tid": "8"
	},
	{
		"name": "cirrus_container-3",
		"cat": "job",
		"ph": "B",
		"ts": "1000000",
		"pid": "0",
		"tid": "3"
	},
	{
		"name": "cirrus_container-6",
		"cat": "job",
		"ph": "B",
		"ts": "2000000",
		"pid": "0",
		"tid": "6"
	},
	{
		"name": "cirrus_container-2",
		"cat": "job",
		"ph": "B",
		"ts": "3000000",
		"pid": "0",
		"tid": "2"
	},
	{
		"name": "cirrus_container-7",
		"cat": "job",
		"ph": "B",
		"ts": "3000000",
		"pid": "0",
		"tid": "7"
	},
	{
		"name": "cirrus_container-1",
		"cat": "job",
		"ph": "B",
		"ts": "4000000",
		"pid": "0",
		"tid": "1"
	},
	{
		"name": "cirrus_container-5",
		"cat": "job",
		"ph": "B",
		"ts": "4000000",
		"pid": "0",
		"tid": "5"
	},
	{
		"name": "cirrus_osx-9",
		"cat": "job",
		"ph": "B",
		"ts": "21000000",
		"pid": "0",
		"tid": "9"
	},
	{
		"name": "cirrus_windows-13",
		"cat": "job",
		"ph": "B",
		"ts": "113000000",
		"pid": "0",
		"tid": "13"
	},
	{
		"name": "cirrus_windows-12",
		"cat": "job",
		"ph": "B",
		"ts": "120000000",
		"pid": "0",
		"tid": "12"
	},
	{
		"name": "cirrus_freebsd-10",
		"cat": "job",
		"ph": "B",
		"ts": "238000000",
		"pid": "0",
		"tid": "10"
	},
	{
		"name": "cirrus_freebsd-11",
		"cat": "job",
		"ph": "B",
		"ts": "245000000",
		"pid": "0",
		"tid": "11"
	},
	{
		"name": "cirrus_container-4",
		"cat": "job",
		"ph": "E",
		"ts": "361000000",
		"pid": "0",
		"tid": "4"
	},
	{
		"name": "cirrus_container-8",
		"cat": "job",
		"ph": "E",
		"ts": "362000000",
		"pid": "0",
		"tid": "8"
	},
	{
		"name": "cirrus_container-3",
		"cat": "job",
		"ph": "E",
		"ts": "362000000",
		"pid": "0",
		"tid": "3"
	},
	{
		"name": "cirrus_container-6",
		"cat": "job",
		"ph": "E",
		"ts": "363000000",
		"pid": "0",
		"tid": "6"
	},
	{
		"name": "cirrus_container-2",
		"cat": "job",
		"ph": "E",
		"ts": "364000000",
		"pid": "0",
		"tid": "2"
	},
	{
		"name": "cirrus_container-7",
		"cat": "job",
		"ph": "E",
		"ts": "364000000",
		"pid": "0",
		"tid": "7"
	},
	{
		"name": "cirrus_container-1",
		"cat": "job",
		"ph": "E",
		"ts": "365000000",
		"pid": "0",
		"tid": "1"
	},
	{
		"name": "cirrus_container-5",
		"cat": "job",
		"ph": "E",
		"ts": "365000000",
		"pid": "0",
		"tid": "5"
	},
	{
		"name": "cirrus_osx-9",
		"cat": "job",
		"ph": "E",
		"ts": "382000000",
		"pid": "0",
		"tid": "9"
	},
	{
		"name": "cirrus_windows-13",
		"cat": "job",
		"ph": "E",
		"ts": "474000000",
		"pid": "0",
		"tid": "13"
	},
	{
		"name": "cirrus_windows-12",
		"cat": "job",
		"ph": "E",
		"ts": "482000000",
		"pid": "0",
		"tid": "12"
	},
	{
		"name": "cirrus_freebsd-10",
		"cat": "job",
		"ph": "E",
		"ts": "601000000",
		"pid": "0",
		"tid": "10"
	},
	{
		"name": "cirrus_freebsd-11",
		"cat": "job",
		"ph": "E",
		"ts": "608000000",
		"pid": "0",
		"tid": "11"
	}
]